hiddifypanel/Events.py
hiddifypanel/VERSION
hiddifypanel/VERSION.py
hiddifypanel/__init__.py
hiddifypanel/__main__.py
hiddifypanel/base.py
hiddifypanel/cache.py
hiddifypanel/development.db
hiddifypanel/drivers/abstract_driver.py
hiddifypanel/drivers/singbox_api.py
hiddifypanel/drivers/ssh_liberty_bridge_api.py
hiddifypanel/drivers/user_driver.py
hiddifypanel/drivers/xray_api.py
hiddifypanel/models/__init__.py
hiddifypanel/models/admin.py
hiddifypanel/models/child.py
hiddifypanel/models/config.py
hiddifypanel/models/config_enum.py
hiddifypanel/models/domain.py
hiddifypanel/models/parent_domain.py
hiddifypanel/models/proxy.py
hiddifypanel/models/report.py
hiddifypanel/models/usage.py
hiddifypanel/models/user.py
hiddifypanel/panel/__init__.py
hiddifypanel/panel/admin_2.py
hiddifypanel/panel/asset.py
hiddifypanel/panel/cf_api.py
hiddifypanel/panel/clean_ip.py
hiddifypanel/panel/cli.py
hiddifypanel/panel/common.py
hiddifypanel/panel/custom_widgets.py
hiddifypanel/panel/database.py
hiddifypanel/panel/hiddify.py
hiddifypanel/panel/init_db.py
hiddifypanel/panel/usage.py
hiddifypanel/panel/admin/Actions.py
hiddifypanel/panel/admin/AdminstratorAdmin.py
hiddifypanel/panel/admin/Backup.py
hiddifypanel/panel/admin/ChildAdmin.py
hiddifypanel/panel/admin/ConfigAdmin.py
hiddifypanel/panel/admin/Dashboard.py
hiddifypanel/panel/admin/DomainAdmin.py
hiddifypanel/panel/admin/ProxyAdmin.py
hiddifypanel/panel/admin/QuickSetup.py
hiddifypanel/panel/admin/SettingAdmin.py
hiddifypanel/panel/admin/Terminal.py
hiddifypanel/panel/admin/UserAdmin.py
hiddifypanel/panel/admin/__init__.py
hiddifypanel/panel/admin/adminlte.py
hiddifypanel/panel/admin/commercial_info.py
hiddifypanel/panel/admin/websocket.py
hiddifypanel/panel/admin/templates/a.html
hiddifypanel/panel/admin/templates/backup.html
hiddifypanel/panel/admin/templates/base.html
hiddifypanel/panel/admin/templates/base2.html
hiddifypanel/panel/admin/templates/commercial_info.html
hiddifypanel/panel/admin/templates/config.html
hiddifypanel_dev-8.0.0.dev29.dist-info/LICENSE.md
hiddifypanel_dev-8.0.0.dev29.dist-info/METADATA
hiddifypanel_dev-8.0.0.dev29.dist-info/WHEEL
hiddifypanel_dev-8.0.0.dev29.dist-info/entry_points.txt
hiddifypanel_dev-8.0.0.dev29.dist-info/top_level.txt
hiddifypanel_dev-8.0.0.dev29.dist-info/RECORD
