Metadata-Version: 2.1
Name: hiddifypanel-dev
Version: 8.0.0.dev29
Summary: hiddifypanel multi proxy panel
Home-page: https://github.com/hiddify/hiddify-config/
Author: hiddify
License-File: LICENSE.md
Requires-Dist: flask (==2.1.3)
Requires-Dist: flask-admin (==1.6.0)
Requires-Dist: bootstrap-flask (==2.2.0)
Requires-Dist: flask-sqlalchemy (==2.5.1)
Requires-Dist: sqlalchemy (==1.4.46)
Requires-Dist: flask-adminlte3
Requires-Dist: sqlalchemy-serializer
Requires-Dist: dynaconf
Requires-Dist: click (==8.1.3)
Requires-Dist: flask-restful
Requires-Dist: sqlalchemy-utils
Requires-Dist: xtlsapi (==3.1.2)
Requires-Dist: python-dateutil
Requires-Dist: flask-babelex
Requires-Dist: babel
Requires-Dist: StrEnum
Requires-Dist: python-dotenv
Requires-Dist: flask-classful
Requires-Dist: werkzeug (==2.1.2)
Requires-Dist: flask-babel
Requires-Dist: gunicorn (==20.1.0)
Requires-Dist: user-agents
Requires-Dist: flask-wtf
Requires-Dist: pyyaml
Requires-Dist: telebot
Requires-Dist: pyuwsgi
Requires-Dist: cython
Requires-Dist: cloudflare
Requires-Dist: maxminddb
Requires-Dist: lastversion
Requires-Dist: psutil
Requires-Dist: h2
Requires-Dist: ping3
Requires-Dist: ansi2html
Requires-Dist: netifaces
Requires-Dist: markupsafe
Requires-Dist: redis
Requires-Dist: python-redis-cache
Requires-Dist: cryptography (>=41.0.0)
Requires-Dist: paramiko
Provides-Extra: test
Requires-Dist: flask-debugtoolbar ; extra == 'test'
Requires-Dist: flask-shell-ipython ; extra == 'test'
Requires-Dist: ipdb ; extra == 'test'
Requires-Dist: pytest-flask ; extra == 'test'
Requires-Dist: python-dotenv ; extra == 'test'
Requires-Dist: pytest ; extra == 'test'
Requires-Dist: coverage ; extra == 'test'
Requires-Dist: flake8 ; extra == 'test'
Requires-Dist: black ; extra == 'test'
Requires-Dist: isort ; extra == 'test'
Requires-Dist: pytest-cov ; extra == 'test'
Requires-Dist: codecov ; extra == 'test'
Requires-Dist: mypy ; extra == 'test'
Requires-Dist: gitchangelog ; extra == 'test'
Requires-Dist: mkdocs ; extra == 'test'
